ship_performance_service_interface_lib/__init__.py
ship_performance_service_interface_lib/sps_interface_pb2.py
ship_performance_service_interface_lib/sps_interface_pb2_grpc.py
ship_performance_service_interface-1.1.9.dist-info/LICENSE
ship_performance_service_interface-1.1.9.dist-info/METADATA
ship_performance_service_interface-1.1.9.dist-info/WHEEL
ship_performance_service_interface-1.1.9.dist-info/top_level.txt
ship_performance_service_interface-1.1.9.dist-info/RECORD
